{
		"name" : {
			"name" : "ts-auth-service",
			"fullName" : "ts-auth-service"
			}
		,
		"entities" : [
			{
				"entityName" : {
					"name" : "AuthDto",
					"fullName" : "AuthDto"
					}
				,
				"fields" : [
					{
						"name" : {
							"name" : "userName",
							"fullName" : "userName"
							}
						,
						"type" : "String",
						"annotations" : [
							]
						,
						"isReference" : false,
						"entityRefName" : null,
						"isCollection" : false
						}
					,
					{
						"name" : {
							"name" : "password",
							"fullName" : "password"
							}
						,
						"type" : "String",
						"annotations" : [
							]
						,
						"isReference" : false,
						"entityRefName" : null,
						"isCollection" : false
						}
					,
					{
						"name" : {
							"name" : "userId",
							"fullName" : "userId"
							}
						,
						"type" : "String",
						"annotations" : [
							]
						,
						"isReference" : false,
						"entityRefName" : null,
						"isCollection" : false
						}
					
					]
				
				}
			,
			{
				"entityName" : {
					"name" : "BasicAuthDto",
					"fullName" : "BasicAuthDto"
					}
				,
				"fields" : [
					{
						"name" : {
							"name" : "verificationCode",
							"fullName" : "verificationCode"
							}
						,
						"type" : "String",
						"annotations" : [
							]
						,
						"isReference" : false,
						"entityRefName" : null,
						"isCollection" : false
						}
					,
					{
						"name" : {
							"name" : "username",
							"fullName" : "username"
							}
						,
						"type" : "String",
						"annotations" : [
							]
						,
						"isReference" : false,
						"entityRefName" : null,
						"isCollection" : false
						}
					,
					{
						"name" : {
							"name" : "password",
							"fullName" : "password"
							}
						,
						"type" : "String",
						"annotations" : [
							]
						,
						"isReference" : false,
						"entityRefName" : null,
						"isCollection" : false
						}
					
					]
				
				}
			,
			{
				"entityName" : {
					"name" : "User",
					"fullName" : "User"
					}
				,
				"fields" : [
					{
						"name" : {
							"name" : "roles",
							"fullName" : "roles"
							}
						,
						"type" : "Set",
						"annotations" : [
							{
								"name" : "@ElementCollection",
								"stringValue" : null,
								"intValue" : null
								}
							,
							{
								"name" : "@CollectionTable",
								"stringValue" : null,
								"intValue" : null
								}
							
							]
						,
						"isReference" : false,
						"entityRefName" : null,
						"isCollection" : false
						}
					,
					{
						"name" : {
							"name" : "userId",
							"fullName" : "userId"
							}
						,
						"type" : "String",
						"annotations" : [
							{
								"name" : "@Id",
								"stringValue" : null,
								"intValue" : null
								}
							,
							{
								"name" : "@Column",
								"stringValue" : null,
								"intValue" : null
								}
							
							]
						,
						"isReference" : false,
						"entityRefName" : null,
						"isCollection" : false
						}
					,
					{
						"name" : {
							"name" : "username",
							"fullName" : "username"
							}
						,
						"type" : "String",
						"annotations" : [
							{
								"name" : "@Column",
								"stringValue" : null,
								"intValue" : null
								}
							
							]
						,
						"isReference" : false,
						"entityRefName" : null,
						"isCollection" : false
						}
					,
					{
						"name" : {
							"name" : "password",
							"fullName" : "password"
							}
						,
						"type" : "String",
						"annotations" : [
							]
						,
						"isReference" : false,
						"entityRefName" : null,
						"isCollection" : false
						}
					
					]
				
				}
			,
			{
				"entityName" : {
					"name" : "TokenDto",
					"fullName" : "TokenDto"
					}
				,
				"fields" : [
					{
						"name" : {
							"name" : "token",
							"fullName" : "token"
							}
						,
						"type" : "String",
						"annotations" : [
							]
						,
						"isReference" : false,
						"entityRefName" : null,
						"isCollection" : false
						}
					,
					{
						"name" : {
							"name" : "username",
							"fullName" : "username"
							}
						,
						"type" : "String",
						"annotations" : [
							]
						,
						"isReference" : false,
						"entityRefName" : null,
						"isCollection" : false
						}
					,
					{
						"name" : {
							"name" : "userId",
							"fullName" : "userId"
							}
						,
						"type" : "String",
						"annotations" : [
							]
						,
						"isReference" : false,
						"entityRefName" : null,
						"isCollection" : false
						}
					
					]
				
				}
			
			]
		,
		"restCalls" : [
			{
				"httpMethod" : "GET",
				"parentMethod" : "auth.service.impl.TokenServiceImpl.getToken",
				"returnType" : "java.lang.Boolean",
				"uri" : "ts-verification-code-service/api/v1/verifycode/verify/",
				"isCollection" : false,
				"restCallInClassName" : "auth.service.impl.TokenServiceImpl",
				"msName" : "ts-auth-service"
				}
			
			]
		,
		"endpoints" : [
			{
				"httpMethod" : "GET",
				"parentMethod" : "auth.controller.AuthController.getHello",
				"arguments" : [
					]
				,
				"returnType" : "java.lang.String",
				"path" : "/hello",
				"isCollection" : false,
				"endpointInClassName" : "auth.controller.AuthController",
				"msName" : "ts-auth-service"
				}
			,
			{
				"httpMethod" : "POST",
				"parentMethod" : "auth.controller.AuthController.createDefaultUser",
				"arguments" : [
					"@RequestBody AuthDto authDto"
					]
				,
				"returnType" : "class org.springframework.http.HttpEntity<class edu.fudan.common.util.Response>",
				"path" : null,
				"isCollection" : true,
				"endpointInClassName" : "auth.controller.AuthController",
				"msName" : "ts-auth-service"
				}
			,
			{
				"httpMethod" : "DELETE",
				"parentMethod" : "auth.controller.UserController.deleteUserById",
				"arguments" : [
					"@PathVariable String userId",
					"@RequestHeader HttpHeaders headers"
					]
				,
				"returnType" : "class org.springframework.http.ResponseEntity<class edu.fudan.common.util.Response>",
				"path" : "/{userId}",
				"isCollection" : true,
				"endpointInClassName" : "auth.controller.UserController",
				"msName" : "ts-auth-service"
				}
			,
			{
				"httpMethod" : "GET",
				"parentMethod" : "auth.controller.UserController.getHello",
				"arguments" : [
					]
				,
				"returnType" : "java.lang.Object",
				"path" : "/hello",
				"isCollection" : false,
				"endpointInClassName" : "auth.controller.UserController",
				"msName" : "ts-auth-service"
				}
			,
			{
				"httpMethod" : "GET",
				"parentMethod" : "auth.controller.UserController.getAllUser",
				"arguments" : [
					"@RequestHeader HttpHeaders headers"
					]
				,
				"returnType" : "class org.springframework.http.ResponseEntity<?>",
				"path" : null,
				"isCollection" : true,
				"endpointInClassName" : "auth.controller.UserController",
				"msName" : "ts-auth-service"
				}
			,
			{
				"httpMethod" : "POST",
				"parentMethod" : "auth.controller.UserController.getToken",
				"arguments" : [
					"@RequestBody BasicAuthDto dao",
					"@RequestHeader HttpHeaders headers"
					]
				,
				"returnType" : "class org.springframework.http.ResponseEntity<class edu.fudan.common.util.Response>",
				"path" : "/login",
				"isCollection" : true,
				"endpointInClassName" : "auth.controller.UserController",
				"msName" : "ts-auth-service"
				}
			
			]
		
		}
	